quick_cd/__init__.py
quick_cd/__main__.py
quick_cd-1.1.1.data/scripts/qcd
quick_cd-1.1.1.dist-info/LICENSE
quick_cd-1.1.1.dist-info/METADATA
quick_cd-1.1.1.dist-info/WHEEL
quick_cd-1.1.1.dist-info/top_level.txt
quick_cd-1.1.1.dist-info/RECORD
