Metadata-Version: 2.1
Name: quick-cd
Version: 1.1.1
Summary: Save working directory under label and cd into it quickly.
Home-page: https://gitlab.com/halftough/quick-cd
Author: HalfTough
Author-email: halftough29A@gmail.com
License: UNKNOWN
Platform: UNKNOWN
Classifier: Programming Language :: Python :: 3
Classifier: License :: OSI Approved :: MIT License
Classifier: Operating System :: POSIX
